README.rst
setup.py
slacker/__init__.py
slacker/utils.py
slacker_asyncio.egg-info/PKG-INFO
slacker_asyncio.egg-info/SOURCES.txt
slacker_asyncio.egg-info/dependency_links.txt
slacker_asyncio.egg-info/requires.txt
slacker_asyncio.egg-info/top_level.txt