Metadata-Version: 1.1
Name: slacker-asyncio
Version: 0.8.6
Summary: Slack API client
Home-page: http://github.com/gfreezy/slacker-asyncio/
Author: gfreezy
Author-email: gfreezy@gmail.com
License: http://www.apache.org/licenses/LICENSE-2.0
Keywords: slack api asyncio
Platform: UNKNOWN
Classifier: Intended Audience :: Developers
Classifier: License :: OSI Approved :: Apache Software License
Classifier: Natural Language :: English
Classifier: Programming Language :: Python
Classifier: Programming Language :: Python :: 3.4
Classifier: Programming Language :: Python :: 3.5
